ysphotutilpy/__init__.py
ysphotutilpy/aperture.py
ysphotutilpy/apphot.py
ysphotutilpy/astroim.py
ysphotutilpy/background.py
ysphotutilpy/center.py
ysphotutilpy/daopsf.py
ysphotutilpy/growth.py
ysphotutilpy/polarimetry.py
ysphotutilpy/query_cols.py
ysphotutilpy/queryutil.py
ysphotutilpy/radprof.py
ysphotutilpy/seputil.py
ysphotutilpy/smallbody.py
ysphotutilpy/util.py
ysphotutilpy/tests/__init__.py
ysphotutilpy/tests/test_apphot.py
ysphotutilpy/tests/test_background.py
ysphotutilpy-0.1.1.dist-info/METADATA
ysphotutilpy-0.1.1.dist-info/WHEEL
ysphotutilpy-0.1.1.dist-info/top_level.txt
ysphotutilpy-0.1.1.dist-info/RECORD
